setup.py
RLToolbox/__init__.py
RLToolbox/parameters.py
RLToolbox.egg-info/PKG-INFO
RLToolbox.egg-info/SOURCES.txt
RLToolbox.egg-info/dependency_links.txt
RLToolbox.egg-info/top_level.txt
RLToolbox/agent/TRPO_agent.py
RLToolbox/agent/TRPO_parallel_agent.py
RLToolbox/agent/__init__.py
RLToolbox/algorithm/TRPO.py
RLToolbox/algorithm/__init__.py
RLToolbox/environment/__init__.py
RLToolbox/environment/gym_environment.py
RLToolbox/experiment/__init__.py
RLToolbox/experiment/trpo_continous.py
RLToolbox/experiment/trpo_parallel.py
RLToolbox/storage/__init__.py
RLToolbox/storage/storage_continous.py
RLToolbox/storage/storage_continous_parallel.py
RLToolbox/toolbox/__init__.py