Metadata-Version: 1.0
Name: RLToolbox
Version: 2.0.3
Summary: rl toolbox
Home-page: https://github.com/jjkke88/RL_toolbox
Author: wuyupei
Author-email: 840302039@qq.com
License: GPL 3.0
Platform: any
